lambda_run/__init__.py
lambda_run/__main__.py
lambda_run/cli.py
lambda_run-0.0.3.dist-info/LICENSE
lambda_run-0.0.3.dist-info/METADATA
lambda_run-0.0.3.dist-info/WHEEL
lambda_run-0.0.3.dist-info/entry_points.txt
lambda_run-0.0.3.dist-info/top_level.txt
lambda_run-0.0.3.dist-info/RECORD
